plinux/__init__.py
plinux/exceptions.py
plinux-2.1.3.dist-info/LICENSE
plinux-2.1.3.dist-info/METADATA
plinux-2.1.3.dist-info/WHEEL
plinux-2.1.3.dist-info/top_level.txt
plinux-2.1.3.dist-info/RECORD
