Metadata-Version: 2.1
Name: plinux
Version: 2.1.3
Summary: The cross-platform SSH tool to execute bash commands remotely.
Author-email: Andrey Komissarov <a.komisssarov@gmail.com>
Project-URL: Homepage, https://github.com/c-pher/plinux
Keywords: SSH,Linux,Windows
Classifier: Programming Language :: Python :: 3
Classifier: License :: OSI Approved :: GNU General Public License v3 (GPLv3)
Classifier: Operating System :: OS Independent
Requires-Python: >=3.10
License-File: LICENSE
Requires-Dist: paramiko >=3.3.1
Requires-Dist: plogger >=1.0.8
